Metadata-Version: 2.1
Name: listenai-seatable-api
Version: 0.0.2
Summary: Python client for SeaTable web api
Home-page: https://github.com/bestjane/seatable-api-python
Author: zh
Author-email: mr.bestjane@gmail.com
License: Apache Licence
Platform: any
Classifier: Programming Language :: Python
Requires-Dist: requests
Requires-Dist: python-socketio
Requires-Dist: ply
Requires-Dist: python-dateutil
